getapt/__init__.py
getapt/_nbdev.py
getapt/apt.py
getapt-0.0.2.dist-info/LICENSE
getapt-0.0.2.dist-info/METADATA
getapt-0.0.2.dist-info/WHEEL
getapt-0.0.2.dist-info/entry_points.txt
getapt-0.0.2.dist-info/top_level.txt
getapt-0.0.2.dist-info/RECORD
