Metadata-Version: 2.1
Name: getapt
Version: 0.0.2
Summary: A python package that gets apartments from craigslist
Home-page: https://github.com/hamelsmu/getapt/tree/master/
Author: Hamel
Author-email: hamel@foo.com
License: Apache Software License 2.0
Keywords: web scraping
Platform: UNKNOWN
Classifier: Development Status :: 3 - Alpha
Classifier: Intended Audience :: Developers
Classifier: Natural Language :: English
Classifier: Programming Language :: Python :: 3.6
Classifier: Programming Language :: Python :: 3.7
Classifier: Programming Language :: Python :: 3.8
Classifier: Programming Language :: Python :: 3.9
Classifier: Programming Language :: Python :: 3.10
Classifier: License :: OSI Approved :: Apache Software License
Requires-Python: >=3.6
License-File: LICENSE
Requires-Dist: pip
Requires-Dist: packaging
Requires-Dist: bs4
Requires-Dist: fastcore
Provides-Extra: dev
